{
  "deployment": {
    "tags": {
      "Environment": "Development",
      "Project": "SAP",
      "ManagedBy": "Terraform"
    },
    
    "foundation": {
      "resource_group": {
        "create": true,
        "name": "rg-200-neu-sap-d-001",
        "location": "North Europe"
      },
      "vnet": {
        "create": true,
        "name": "vnet-200-neu-sap-d-001",
        "address_space": "10.160.0.0/16"
      },
      "subnet": {
        "create": true,
        "name": "snet-200-neu-sap-d-app-001",
        "address_prefix": "10.160.41.0/24"
      }
    },
    
    "compute": {
      "vms": {
        "200mywizp017": {
          "size": "Standard_B1s",
          "admin_username": "azlinuxadmin",
          "ssh_public_key_path": "../keys/id_rsa.pub",
          "enable_public_ip": true,
          "private_ip_address": "10.160.41.6",
          "os_disk_type": "Premium_LRS",
          "os_disk_size_gb": 64,
          "image": {
            "publisher": "Canonical",
            "offer": "0001-com-ubuntu-server-jammy",
            "sku": "22_04-lts-gen2",
            "version": "latest"
          },
          "data_disks": [
            {
              "name": "data01",
              "disk_size_gb": 4,
              "storage_account_type": "Premium_LRS",
              "lun": 0
            }
          ]
        }
      }
    }
  }
}